{
  "LastUpdated": "2025-03-16T16:40:36.3911403-07:00",
  "Streets": {
    "Balfour Ave": "SAFE",
    "E Santa Fe Ave": "SAFE",
    "Riverside Dr": "SAFE",
    "Teri Pl": "NOT SAFE"
  },
  "RecentCalls": [
    {
      "Incident": "25-13744",
      "Type": "DISTURBANCE OF PEACE",
      "Date": "03/16/2025 4:29 PM",
      "Address": "MILTON AVE / TERI PL"
    },
    {
      "Incident": "25-13743",
      "Type": "PARKING PROBLEM",
      "Date": "03/16/2025 4:24 PM",
      "Address": "2600 BLOCK ANDOVER AVE"
    }
  ]
}